asd_py/__init__.py
asd_py/linear_fit.py
asd_py/ml_fit.py
asd_py/preprocess.py
asd_py/spectral_index.py
asd_py-0.1.dist-info/LICENSE
asd_py-0.1.dist-info/METADATA
asd_py-0.1.dist-info/WHEEL
asd_py-0.1.dist-info/top_level.txt
asd_py-0.1.dist-info/RECORD
