Metadata-Version: 2.1
Name: asd-py
Version: 0.1
Summary: site(canopy)/leaf hyperspectral proccessing program by python
Home-page: https://github.com/justinG-29/asd_py
Author: Justin Guo
Author-email: guojianbiao2008@gmail.com
License: MIT
Platform: UNKNOWN
Classifier: Development Status :: 3 - Alpha
Classifier: Intended Audience :: Science/Research
Classifier: Topic :: Scientific/Engineering :: Atmospheric Science
Classifier: Programming Language :: Python :: 3
Requires-Python: >=3
Requires-Dist: numpy
Requires-Dist: pandas
Requires-Dist: scipy
Requires-Dist: plotly
Requires-Dist: scikit-learn
Provides-Extra: read_asd_data
Requires-Dist: specdal ; extra == 'read_asd_data'
